bentoml/__init__.py
bentoml/__main__.py
bentoml/_version.py
bentoml/batch.py
bentoml/bentos.py
bentoml/catboost.py
bentoml/client.py
bentoml/container.py
bentoml/detectron.py
bentoml/diffusers.py
bentoml/easyocr.py
bentoml/evalml.py
bentoml/exceptions.py
bentoml/fastai.py
bentoml/fasttext.py
bentoml/flax.py
bentoml/gluon.py
bentoml/h2o.py
bentoml/io.py
bentoml/keras.py
bentoml/lightgbm.py
bentoml/metrics.py
bentoml/metrics.pyi
bentoml/mlflow.py
bentoml/models.py
bentoml/monitoring.py
bentoml/onnx.py
bentoml/onnxmlir.py
bentoml/paddle.py
bentoml/picklable_model.py
bentoml/py.typed
bentoml/pycaret.py
bentoml/pyspark.py
bentoml/pytorch.py
bentoml/pytorch_lightning.py
bentoml/ray.py
bentoml/serve.py
bentoml/server.py
bentoml/sklearn.py
bentoml/spacy.py
bentoml/start.py
bentoml/statsmodels.py
bentoml/tensorflow.py
bentoml/tensorflow_v1.py
bentoml/torchscript.py
bentoml/transformers.py
bentoml/triton.py
bentoml/types.py
bentoml/xgboost.py
bentoml/_internal/__init__.py
bentoml/_internal/context.py
bentoml/_internal/exportable.py
bentoml/_internal/log.py
bentoml/_internal/resource.py
bentoml/_internal/store.py
bentoml/_internal/tag.py
bentoml/_internal/types.py
bentoml/_internal/batch/__init__.py
bentoml/_internal/batch/spark.py
bentoml/_internal/bento/__init__.py
bentoml/_internal/bento/bento.py
bentoml/_internal/bento/build_config.py
bentoml/_internal/bento/build_dev_bentoml_whl.py
bentoml/_internal/bento/gen.py
bentoml/_internal/client/__init__.py
bentoml/_internal/client/grpc.py
bentoml/_internal/client/http.py
bentoml/_internal/configuration/__init__.py
bentoml/_internal/configuration/containers.py
bentoml/_internal/configuration/helpers.py
bentoml/_internal/configuration/v1/__init__.py
bentoml/_internal/configuration/v1/default_configuration.yaml
bentoml/_internal/container/__init__.py
bentoml/_internal/container/base.py
bentoml/_internal/container/buildah.py
bentoml/_internal/container/buildctl.py
bentoml/_internal/container/buildx.py
kentoml-1.0.20.post11.dist-info/LICENSE
kentoml-1.0.20.post11.dist-info/METADATA
kentoml-1.0.20.post11.dist-info/WHEEL
kentoml-1.0.20.post11.dist-info/entry_points.txt
kentoml-1.0.20.post11.dist-info/top_level.txt
kentoml-1.0.20.post11.dist-info/RECORD
